pakkr/__init__.py
pakkr/exception.py
pakkr/exception_test.py
pakkr/logging.py
pakkr/logging_test.py
pakkr/pipeline.py
pakkr/pipeline_test.py
pakkr/cmd_args/__init__.py
pakkr/cmd_args/argument.py
pakkr/cmd_args/argument_test.py
pakkr/cmd_args/cmd_args.py
pakkr/cmd_args/cmd_args_test.py
pakkr/returns/__init__.py
pakkr/returns/_meta.py
pakkr/returns/_meta_test.py
pakkr/returns/_no_return.py
pakkr/returns/_no_return_test.py
pakkr/returns/_return.py
pakkr/returns/_return_test.py
pakkr/returns/returns.py
pakkr/returns/returns_test.py
pakkr-0.1.0.dist-info/LICENSE
pakkr-0.1.0.dist-info/METADATA
pakkr-0.1.0.dist-info/WHEEL
pakkr-0.1.0.dist-info/top_level.txt
pakkr-0.1.0.dist-info/RECORD
