Metadata-Version: 2.1
Name: pakkr
Version: 0.1.0
Summary: Pipeline utility library
Home-page: https://github.com/zendesk/pakkr
Maintainer: Zendesk
Maintainer-email: opensource@zendesk.com
License: Apache License 2.0
Platform: UNKNOWN
Classifier: License :: OSI Approved :: Apache Software License
Classifier: Programming Language :: Python :: 3.6
Classifier: Programming Language :: Python :: 3.7
Classifier: Programming Language :: Python :: 3.8
Classifier: Topic :: Utilities
Requires-Python: >=3.6
